<?xml version="1.0"?>
<!DOCTYPE hibernate-mapping PUBLIC "-//Hibernate/Hibernate Mapping DTD 3.0//EN"
"http://www.hibernate.org/dtd/hibernate-mapping-3.0.dtd">
<!-- Generated Oct 8, 2019 2:59:35 PM by Hibernate Tools 4.3.1 -->
<hibernate-mapping>
    <class name="pojo.ImageTable" table="image_table" catalog="chairty" optimistic-lock="version">
        <id name="id" type="java.lang.Integer">
            <column name="id" />
            <generator class="identity" />
        </id>
        <property name="image" type="binary">
            <column name="image" />
        </property>
    </class>
</hibernate-mapping>
